acp_mcp_server/__init__.py
acp_mcp_server/__main__.py
acp_mcp_server/agent_discovery.py
acp_mcp_server/agent_router.py
acp_mcp_server/interactive_manager.py
acp_mcp_server/message_bridge.py
acp_mcp_server/run_orchestrator.py
acp_mcp_server/server.py
acp_mcp_server-0.0.5.dist-info/METADATA
acp_mcp_server-0.0.5.dist-info/WHEEL
acp_mcp_server-0.0.5.dist-info/entry_points.txt
acp_mcp_server-0.0.5.dist-info/licenses/LICENSE
acp_mcp_server-0.0.5.dist-info/RECORD
