Metadata-Version: 2.4
Name: acp-mcp-server
Version: 0.0.5
Summary: Bridge server connecting Agent Communication Protocol (ACP) agents with Model Context Protocol (MCP) clients
Project-URL: Homepage, https://github.com/GongRzhe/ACP-MCP-Server
Project-URL: Documentation, https://github.com/GongRzhe/ACP-MCP-Server#readme
Project-URL: Repository, https://github.com/GongRzhe/ACP-MCP-Server
Project-URL: Bug Tracker, https://github.com/GongRzhe/ACP-MCP-Server/issues
Project-URL: Changelog, https://github.com/GongRzhe/ACP-MCP-Server/blob/main/CHANGELOG.md
Author-email: GongRzhe <gongrzhe@gmail.com>
Maintainer-email: GongRzhe <your.email@example.com>
License: MIT
License-File: LICENSE
Keywords: acp,agent-communication-protocol,ai-agents,anthropic,bridge-server,claude,mcp,model-context-protocol
Classifier: Development Status :: 4 - Beta
Classifier: Intended Audience :: Developers
Classifier: License :: OSI Approved :: MIT License
Classifier: Operating System :: OS Independent
Classifier: Programming Language :: Python :: 3
Classifier: Programming Language :: Python :: 3.11
Classifier: Programming Language :: Python :: 3.12
Classifier: Topic :: Communications
Classifier: Topic :: Internet :: WWW/HTTP :: HTTP Servers
Classifier: Topic :: Scientific/Engineering :: Artificial Intelligence
Classifier: Topic :: Software Development :: Libraries :: Python Modules
Requires-Python: >=3.11
Requires-Dist: aiohttp>=3.9.0
Requires-Dist: fastmcp>=2.8.1
Requires-Dist: pydantic>=2.0.0
Requires-Dist: uvicorn>=0.27.0
Provides-Extra: dev
Requires-Dist: black>=23.0.0; extra == 'dev'
Requires-Dist: isort>=5.12.0; extra == 'dev'
Requires-Dist: mypy>=1.5.0; extra == 'dev'
Requires-Dist: pre-commit>=3.0.0; extra == 'dev'
Requires-Dist: pytest-asyncio>=0.21.0; extra == 'dev'
Requires-Dist: pytest>=7.0.0; extra == 'dev'
